Workbook

Sheet 门店
A1: 营业额 | B1: 门店 | D1: 总和 | E1: =SUM(A:A) -> 101198.66 | G1: =看板表!C18 -> 115631.46
A2: =SUMIF(数据源表A!B:B,B2,数据源表A!F:F) -> 3695.02 | B2: 鹅太公烧鹅（上排店）
A3: =SUMIF(数据源表A!B:B,B3,数据源表A!F:F) -> 5924.51 | B3: 鹅太公烧鹅（下埔店）
A4: =SUMIF(数据源表A!B:B,B4,数据源表A!F:F) -> 3425.3 | B4: 鹅太公烧鹅（东平三院店）
A5: =SUMIF(数据源表A!B:B,B5,数据源表A!F:F) -> 5636.46 | B5: 鹅太公烧鹅（东平半岛店）
A6: =SUMIF(数据源表A!B:B,B6,数据源表A!F:F) -> 5649.76 | B6: 鹅太公烧鹅（华侨城店）
A7: =SUMIF(数据源表A!B:B,B7,数据源表A!F:F) -> 9381.7 | B7: 鹅太公烧鹅（博罗店）
A8: =SUMIF(数据源表A!B:B,B8,数据源表A!F:F) -> 8178.26 | B8: 鹅太公烧鹅（坂田店）
A9: =SUMIF(数据源表A!B:B,B9,数据源表A!F:F) -> 3972 | B9: 鹅太公烧鹅（方洲店）
A10: =SUMIF(数据源表A!B:B,B10,数据源表A!F:F) -> 6075.55 | B10: 鹅太公烧鹅（普宁店）
A11: =SUMIF(数据源表A!B:B,B11,数据源表A!F:F) -> 7770.7 | B11: 鹅太公烧鹅（普宁溪尾店）
A12: =SUMIF(数据源表A!B:B,B12,数据源表A!F:F) -> 0 | B12: 鹅太公烧鹅（未来城店）
A13: =SUMIF(数据源表A!B:B,B13,数据源表A!F:F) -> 8533.79 | B13: 鹅太公烧鹅（欧景花园店）
... A18: =SUMIF(数据源表A!B:B,B18,数据源表A!F:F) -> 9979.48 | B18: 鹅太公烧鹅（龙岗万科店）

Sheet 看板表
A1: 收 银 系 统 每 日 高 低 位 数 据
A3: 46218
A5: 排名 | B5: 门店名称 | C5: 营业额 | D5: 实收 | E5: 有效订单 | F5: 实收 | K5: 一键买单（尾款） | L5: 美团团购 | M5: 抖音团购 | N5: 会员卡 | O5: 优惠券 | P5: 店内+自提收入 | Q5: 优惠金额 | R5: 优惠占比
F6: 店内销售 | G6: 自提销售 | H6: 美团外卖 | I6: 淘宝闪购 | J6: 京东外卖 | K6: 美团一键买单 | L6: 美团团购 | M6: 抖音团购 | N6: 储值消费 | O6: 优惠券
A7: TOP1 | B7: =VLOOKUP(LARGE(门店!A:A,1),门店!A:B,2,FALSE) -> 鹅太公烧鹅（龙岗万科店） | C7: =SUMIF(数据源表A!B:B,B7,数据源表A!F:F) -> 9979.48 | D7: =SUMIF(数据源表A!B:B,B7,数据源表A!H:H) -> 5875.7 | E7: =SUMIF(数据源表A!B:B,B7,数据源表A!I:I) -> 179 | F7: =SUMIF(数据源表A!B:B,B7,数据源表A!U:U) -> 2736.87 | G7: =SUMIF(数据源表A!B:B,B7,数据源表A!AA:AA) -> 0 | H7: =SUMIF(数据源表A!B:B,B7,数据源表A!AG:AG) -> 1980.31 | I7: =SUMIF(数据源表A!B:B,B7,数据源表A!AM:AM) -> 1158.52 | J7: =SUMIF(数据源表A!B:B,B7,数据源表A!AS:AS) -> 0 | K7: =SUMIF(数据源表A!$B:$B,$B7,INDEX(数据源表A!$A:$CA,0,MATCH(K$5,数据源表A!$2:$2,0))) -> 8 | L7: =IFERROR(SUMIF(数据源表A!$B:$B,$B7,INDEX(数据源表A!$A:$CA,0,MATCH("美团/大众点评团购",数据源表A!$2:$2,0))),0)+IFERROR(SUMIF(数据源表A!$B:$B,$B7,INDEX(数据源表A!$A:$CA,0,MATCH("美团/大众点评支付",数据源表A!$2:$2,0))),0) -> 503.38 | M7: =SUMIF(数据源表A!$B:$B,$B7,INDEX(数据源表A!$A:$CA,0,MATCH(M$5,数据源表A!$2:$2,0))) -> 339.4 | N7: =SUMIF(数据源表A!$B:$B,$B7,INDEX(数据源表A!$A:$CA,0,MATCH(N$5,数据源表A!$2:$2,0))) -> 2.09 | O7: =IFERROR(SUMIF(数据源表A!$B:$B,$B7,INDEX(数据源表A!$A:$CA,0,MATCH(O$5,数据源表A!$2:$2,0))),0) -> 0 | P7: =F7-L7-M7+G7-K7-N7-O7 -> 1884 | Q7: =SUMIF(数据源表A!B:B,B7,数据源表A!G:G) -> 4103.78 | R7: =Q7/C7 -> 0.41122183
A8: TOP2 | B8: =VLOOKUP(LARGE(门店!A:A,2),门店!A:B,2,FALSE) -> 鹅太公烧鹅（博罗店） | C8: =SUMIF(数据源表A!B:B,B8,数据源表A!F:F) -> 9381.7 | D8: =SUMIF(数据源表A!B:B,B8,数据源表A!H:H) -> 6126.51 | E8: =SUMIF(数据源表A!B:B,B8,数据源表A!I:I) -> 219 | F8: =SUMIF(数据源表A!B:B,B8,数据源表A!U:U) -> 4296.12 | G8: =SUMIF(数据源表A!B:B,B8,数据源表A!AA:AA) -> 0 | H8: =SUMIF(数据源表A!B:B,B8,数据源表A!AG:AG) -> 874.4 | I8: =SUMIF(数据源表A!B:B,B8,数据源表A!AM:AM) -> 955.99 | J8: =SUMIF(数据源表A!B:B,B8,数据源表A!AS:AS) -> 0 | K8: =SUMIF(数据源表A!$B:$B,$B8,INDEX(数据源表A!$A:$CA,0,MATCH(K$5,数据源表A!$2:$2,0))) -> 0 | L8: =IFERROR(SUMIF(数据源表A!$B:$B,$B8,INDEX(数据源表A!$A:$CA,0,MATCH("美团/大众点评团购",数据源表A!$2:$2,0))),0)+IFERROR(SUMIF(数据源表A!$B:$B,$B8,INDEX(数据源表A!$A:$CA,0,MATCH("美团/大众点评支付",数据源表A!$2:$2,0))),0) -> 141.2 | M8: =SUMIF(数据源表A!$B:$B,$B8,INDEX(数据源表A!$A:$CA,0,MATCH(M$5,数据源表A!$2:$2,0))) -> 320.1 | N8: =SUMIF(数据源表A!$B:$B,$B8,INDEX(数据源表A!$A:$CA,0,MATCH(N$5,数据源表A!$2:$2,0))) -> 35.62 | O8: =IFERROR(SUMIF(数据源表A!$B:$B,$B8,INDEX(数据源表A!$A:$CA,0,MATCH(O$5,数据源表A!$2:$2,0))),0) -> 0 | P8: =F8-L8-M8+G8-K8-N8-O8 -> 3799.2 | Q8: =SUMIF(数据源表A!B:B,B8,数据源表A!G:G) -> 3255.19 | R8: =Q8/C8 -> 0.3469723
A9: TOP3 | B9: =VLOOKUP(LARGE(门店!A:A,3),门店!A:B,2,FALSE) -> 鹅太公烧鹅（欧景花园店） | C9: =SUMIF(数据源表A!B:B,B9,数据源表A!F:F) -> 8533.79 | D9: =SUMIF(数据源表A!B:B,B9,数据源表A!H:H) -> 5619.35 | E9: =SUMIF(数据源表A!B:B,B9,数据源表A!I:I) -> 157 | F9: =SUMIF(数据源表A!B:B,B9,数据源表A!U:U) -> 3158.41 | G9: =SUMIF(数据源表A!B:B,B9,数据源表A!AA:AA) -> 88.8 | H9: =SUMIF(数据源表A!B:B,B9,数据源表A!AG:AG) -> 1774.7 | I9: =SUMIF(数据源表A!B:B,B9,数据源表A!AM:AM) -> 597.44 | J9: =SUMIF(数据源表A!B:B,B9,数据源表A!AS:AS) -> 0 | K9: =SUMIF(数据源表A!$B:$B,$B9,INDEX(数据源表A!$A:$CA,0,MATCH(K$5,数据源表A!$2:$2,0))) -> 13 | L9: =IFERROR(SUMIF(数据源表A!$B:$B,$B9,INDEX(数据源表A!$A:$CA,0,MATCH("美团/大众点评团购",数据源表A!$2:$2,0))),0)+IFERROR(SUMIF(数据源表A!$B:$B,$B9,INDEX(数据源表A!$A:$CA,0,MATCH("美团/大众点评支付",数据源表A!$2:$2,0))),0) -> 376.84 | M9: =SUMIF(数据源表A!$B:$B,$B9,INDEX(数据源表A!$A:$CA,0,MATCH(M$5,数据源表A!$2:$2,0))) -> 298.64 | N9: =SUMIF(数据源表A!$B:$B,$B9,INDEX(数据源表A!$A:$CA,0,MATCH(N$5,数据源表A!$2:$2,0))) -> 65.73 | O9: =IFERROR(SUMIF(数据源表A!$B:$B,$B9,INDEX(数据源表A!$A:$CA,0,MATCH(O$5,数据源表A!$2:$2,0))),0) -> 0 | P9: =F9-L9-M9+G9-K9-N9-O9 -> 2493 | Q9: =SUMIF(数据源表A!B:B,B9,数据源表A!G:G) -> 2914.44 | R9: =Q9/C9 -> 0.34151766
A11: 7 | B11: =VLOOKUP(LARGE(门店!A:A,7),门店!A:B,2,FALSE) -> 鹅太公烧鹅（麦地店） | C11: =SUMIF(数据源表A!B:B,B11,数据源表A!F:F) -> 7043.29 | D11: =SUMIF(数据源表A!B:B,B11,数据源表A!H:H) -> 4211.36 | E11: =SUMIF(数据源表A!B:B,B11,数据源表A!I:I) -> 170 | F11: =SUMIF(数据源表A!B:B,B11,数据源表A!U:U) -> 2020.74 | G11: =SUMIF(数据源表A!B:B,B11,数据源表A!AA:AA) -> 0 | H11: =SUMIF(数据源表A!B:B,B11,数据源表A!AG:AG) -> 846.42 | I11: =SUMIF(数据源表A!B:B,B11,数据源表A!AM:AM) -> 1264.35 | J11: =SUMIF(数据源表A!B:B,B11,数据源表A!AS:AS) -> 79.85 | K11: =SUMIF(数据源表A!$B:$B,$B11,INDEX(数据源表A!$A:$CA,0,MATCH(K$5,数据源表A!$2:$2,0))) -> 0 | L11: =IFERROR(SUMIF(数据源表A!$B:$B,$B11,INDEX(数据源表A!$A:$CA,0,MATCH("美团/大众点评团购",数据源表A!$2:$2,0))),0)+IFERROR(SUMIF(数据源表A!$B:$B,$B11,INDEX(数据源表A!$A:$CA,0,MATCH("美团/大众点评支付",数据源表A!$2:$2,0))),0) -> 216.86 | M11: =SUMIF(数据源表A!$B:$B,$B11,INDEX(数据源表A!$A:$CA,0,MATCH(M$5,数据源表A!$2:$2,0))) -> 327.8 | N11: =SUMIF(数据源表A!$B:$B,$B11,INDEX(数据源表A!$A:$CA,0,MATCH(N$5,数据源表A!$2:$2,0))) -> 58.08 | O11: =IFERROR(SUMIF(数据源表A!$B:$B,$B11,INDEX(数据源表A!$A:$CA,0,MATCH(O$5,数据源表A!$2:$2,0))),0) -> 0 | P11: =F11-L11-M11+G11-K11-N11-O11 -> 1418 | Q11: =SUMIF(数据源表A!B:B,B11,数据源表A!G:G) -> 2831.93 | R11: =Q11/C11 -> 0.40207488
A12: 8 | B12: =VLOOKUP(LARGE(门店!A:A,8),门店!A:B,2,FALSE) -> 鹅太公烧鹅（普宁店） | C12: =SUMIF(数据源表A!B:B,B12,数据源表A!F:F) -> 6075.55 | D12: =SUMIF(数据源表A!B:B,B12,数据源表A!H:H) -> 3957.76 | E12: =SUMIF(数据源表A!B:B,B12,数据源表A!I:I) -> 164 | F12: =SUMIF(数据源表A!B:B,B12,数据源表A!U:U) -> 2236.42 | G12: =SUMIF(数据源表A!B:B,B12,数据源表A!AA:AA) -> 0 | H12: =SUMIF(数据源表A!B:B,B12,数据源表A!AG:AG) -> 412.86 | I12: =SUMIF(数据源表A!B:B,B12,数据源表A!AM:AM) -> 718.17 | J12: =SUMIF(数据源表A!B:B,B12,数据源表A!AS:AS) -> 590.31 | K12: =SUMIF(数据源表A!$B:$B,$B12,INDEX(数据源表A!$A:$CA,0,MATCH(K$5,数据源表A!$2:$2,0))) -> 0 | L12: =IFERROR(SUMIF(数据源表A!$B:$B,$B12,INDEX(数据源表A!$A:$CA,0,MATCH("美团/大众点评团购",数据源表A!$2:$2,0))),0)+IFERROR(SUMIF(数据源表A!$B:$B,$B12,INDEX(数据源表A!$A:$CA,0,MATCH("美团/大众点评支付",数据源表A!$2:$2,0))),0) -> 23.8 | M12: =SUMIF(数据源表A!$B:$B,$B12,INDEX(数据源表A!$A:$CA,0,MATCH(M$5,数据源表A!$2:$2,0))) -> 381.71 | N12: =SUMIF(数据源表A!$B:$B,$B12,INDEX(数据源表A!$A:$CA,0,MATCH(N$5,数据源表A!$2:$2,0))) -> 21.91 | O12: =IFERROR(SUMIF(数据源表A!$B:$B,$B12,INDEX(数据源表A!$A:$CA,0,MATCH(O$5,数据源表A!$2:$2,0))),0) -> 0 | P12: =F12-L12-M12+G12-K12-N12-O12 -> 1809 | Q12: =SUMIF(数据源表A!B:B,B12,数据源表A!G:G) -> 2117.79 | R12: =Q12/C12 -> 0.34857585
A13: 9 | B13: =VLOOKUP(LARGE(门店!A:A,9),门店!A:B,2,FALSE) -> 鹅太公烧鹅（下埔店） | C13: =SUMIF(数据源表A!B:B,B13,数据源表A!F:F) -> 5924.51 | D13: =SUMIF(数据源表A!B:B,B13,数据源表A!H:H) -> 4309.55 | E13: =SUMIF(数据源表A!B:B,B13,数据源表A!I:I) -> 140 | F13: =SUMIF(数据源表A!B:B,B13,数据源表A!U:U) -> 2982.35 | G13: =SUMIF(数据源表A!B:B,B13,数据源表A!AA:AA) -> 0 | H13: =SUMIF(数据源表A!B:B,B13,数据源表A!AG:AG) -> 586.99 | I13: =SUMIF(数据源表A!B:B,B13,数据源表A!AM:AM) -> 464.87 | J13: =SUMIF(数据源表A!B:B,B13,数据源表A!AS:AS) -> 275.34 | K13: =SUMIF(数据源表A!$B:$B,$B13,INDEX(数据源表A!$A:$CA,0,MATCH(K$5,数据源表A!$2:$2,0))) -> 0 | L13: =IFERROR(SUMIF(数据源表A!$B:$B,$B13,INDEX(数据源表A!$A:$CA,0,MATCH("美团/大众点评团购",数据源表A!$2:$2,0))),0)+IFERROR(SUMIF(数据源表A!$B:$B,$B13,INDEX(数据源表A!$A:$CA,0,MATCH("美团/大众点评支付",数据源表A!$2:$2,0))),0) -> 105.2 | M13: =SUMIF(数据源表A!$B:$B,$B13,INDEX(数据源表A!$A:$CA,0,MATCH(M$5,数据源表A!$2:$2,0))) -> 253.1 | N13: =SUMIF(数据源表A!$B:$B,$B13,INDEX(数据源表A!$A:$CA,0,MATCH(N$5,数据源表A!$2:$2,0))) -> 36.2 | O13: =IFERROR(SUMIF(数据源表A!$B:$B,$B13,INDEX(数据源表A!$A:$CA,0,MATCH(O$5,数据源表A!$2:$2,0))),0) -> 0 | P13: =F13-L13-M13+G13-K13-N13-O13 -> 2587.85 | Q13: =SUMIF(数据源表A!B:B,B13,数据源表A!G:G) -> 1614.96 | R13: =Q13/C13 -> 0.27258963
A15: 最差3 | B15: {=VLOOKUP(_xlfn.AGGREGATE(15,6,门店!A:A/(门店!A:A>0),3),门店!A:B,2,FALSE)} -> 鹅太公烧鹅（上排店） | C15: =SUMIF(数据源表A!B:B,B15,数据源表A!F:F) -> 3695.02 | D15: =SUMIF(数据源表A!B:B,B15,数据源表A!H:H) -> 2248.29 | E15: =SUMIF(数据源表A!B:B,B15,数据源表A!I:I) -> 93 | F15: =SUMIF(数据源表A!B:B,B15,数据源表A!U:U) -> 1272.32 | G15: =SUMIF(数据源表A!B:B,B15,数据源表A!AA:AA) -> 0 | H15: =SUMIF(数据源表A!B:B,B15,数据源表A!AG:AG) -> 427.09 | I15: =SUMIF(数据源表A!B:B,B15,数据源表A!AM:AM) -> 432.07 | J15: =SUMIF(数据源表A!B:B,B15,数据源表A!AS:AS) -> 116.81 | K15: =SUMIF(数据源表A!$B:$B,$B15,INDEX(数据源表A!$A:$CA,0,MATCH(K$5,数据源表A!$2:$2,0))) -> 0 | L15: =IFERROR(SUMIF(数据源表A!$B:$B,$B15,INDEX(数据源表A!$A:$CA,0,MATCH("美团/大众点评团购",数据源表A!$2:$2,0))),0)+IFERROR(SUMIF(数据源表A!$B:$B,$B15,INDEX(数据源表A!$A:$CA,0,MATCH("美团/大众点评支付",数据源表A!$2:$2,0))),0) -> 64.4 | M15: =SUMIF(数据源表A!$B:$B,$B15,INDEX(数据源表A!$A:$CA,0,MATCH(M$5,数据源表A!$2:$2,0))) -> 173.4 | N15: =SUMIF(数据源表A!$B:$B,$B15,INDEX(数据源表A!$A:$CA,0,MATCH(N$5,数据源表A!$2:$2,0))) -> 0 | O15: =IFERROR(SUMIF(数据源表A!$B:$B,$B15,INDEX(数据源表A!$A:$CA,0,MATCH(O$5,数据源表A!$2:$2,0))),0) -> 0 | P15: =F15-L15-M15+G15-K15-N15-O15 -> 1034.52 | Q15: =SUMIF(数据源表A!B:B,B15,数据源表A!G:G) -> 1446.73 | R15: =IFERROR(Q15/C15,"") -> 0.39153509
A16: 最差2 | B16: {=VLOOKUP(_xlfn.AGGREGATE(15,6,门店!A:A/(门店!A:A>0),2),门店!A:B,2,FALSE)} -> 鹅太公烧鹅（水口店） | C16: =SUMIF(数据源表A!B:B,B16,数据源表A!F:F) -> 3644.8 | D16: =SUMIF(数据源表A!B:B,B16,数据源表A!H:H) -> 2630.37 | E16: =SUMIF(数据源表A!B:B,B16,数据源表A!I:I) -> 91 | F16: =SUMIF(数据源表A!B:B,B16,数据源表A!U:U) -> 1663.8 | G16: =SUMIF(数据源表A!B:B,B16,数据源表A!AA:AA) -> 0 | H16: =SUMIF(数据源表A!B:B,B16,数据源表A!AG:AG) -> 387.33 | I16: =SUMIF(数据源表A!B:B,B16,数据源表A!AM:AM) -> 284.45 | J16: =SUMIF(数据源表A!B:B,B16,数据源表A!AS:AS) -> 294.79 | K16: =SUMIF(数据源表A!$B:$B,$B16,INDEX(数据源表A!$A:$CA,0,MATCH(K$5,数据源表A!$2:$2,0))) -> 0 | L16: =IFERROR(SUMIF(数据源表A!$B:$B,$B16,INDEX(数据源表A!$A:$CA,0,MATCH("美团/大众点评团购",数据源表A!$2:$2,0))),0)+IFERROR(SUMIF(数据源表A!$B:$B,$B16,INDEX(数据源表A!$A:$CA,0,MATCH("美团/大众点评支付",数据源表A!$2:$2,0))),0) -> 23.8 | M16: =SUMIF(数据源表A!$B:$B,$B16,INDEX(数据源表A!$A:$CA,0,MATCH(M$5,数据源表A!$2:$2,0))) -> 216.4 | N16: =SUMIF(数据源表A!$B:$B,$B16,INDEX(数据源表A!$A:$CA,0,MATCH(N$5,数据源表A!$2:$2,0))) -> 0 | O16: =IFERROR(SUMIF(数据源表A!$B:$B,$B16,INDEX(数据源表A!$A:$CA,0,MATCH(O$5,数据源表A!$2:$2,0))),0) -> 0 | P16: =F16-L16-M16+G16-K16-N16-O16 -> 1423.6 | Q16: =SUMIF(数据源表A!B:B,B16,数据源表A!G:G) -> 1014.43 | R16: =IFERROR(Q16/C16,"") -> 0.27832254
A17: 最差1 | B17: {=VLOOKUP(_xlfn.AGGREGATE(15,6,门店!A:A/(门店!A:A>0),1),门店!A:B,2,FALSE)} -> 鹅太公烧鹅（东平三院店） | C17: =SUMIF(数据源表A!B:B,B17,数据源表A!F:F) -> 3425.3 | D17: =SUMIF(数据源表A!B:B,B17,数据源表A!H:H) -> 3036.31 | E17: =SUMIF(数据源表A!B:B,B17,数据源表A!I:I) -> 92 | F17: =SUMIF(数据源表A!B:B,B17,数据源表A!U:U) -> 2754.9 | G17: =SUMIF(数据源表A!B:B,B17,数据源表A!AA:AA) -> 0 | H17: =SUMIF(数据源表A!B:B,B17,数据源表A!AG:AG) -> 281.41 | I17: =SUMIF(数据源表A!B:B,B17,数据源表A!AM:AM) -> 0 | J17: =SUMIF(数据源表A!B:B,B17,数据源表A!AS:AS) -> 0 | K17: =SUMIF(数据源表A!$B:$B,$B17,INDEX(数据源表A!$A:$CA,0,MATCH(K$5,数据源表A!$2:$2,0))) -> 0 | L17: =IFERROR(SUMIF(数据源表A!$B:$B,$B17,INDEX(数据源表A!$A:$CA,0,MATCH("美团/大众点评团购",数据源表A!$2:$2,0))),0)+IFERROR(SUMIF(数据源表A!$B:$B,$B17,INDEX(数据源表A!$A:$CA,0,MATCH("美团/大众点评支付",数据源表A!$2:$2,0))),0) -> 61.6 | M17: =SUMIF(数据源表A!$B:$B,$B17,INDEX(数据源表A!$A:$CA,0,MATCH(M$5,数据源表A!$2:$2,0))) -> 103.3 | N17: =SUMIF(数据源表A!$B:$B,$B17,INDEX(数据源表A!$A:$CA,0,MATCH(N$5,数据源表A!$2:$2,0))) -> 0 | O17: =IFERROR(SUMIF(数据源表A!$B:$B,$B17,INDEX(数据源表A!$A:$CA,0,MATCH(O$5,数据源表A!$2:$2,0))),0) -> 0 | P17: =F17-L17-M17+G17-K17-N17-O17 -> 2590 | Q17: =SUMIF(数据源表A!B:B,B17,数据源表A!G:G) -> 388.99 | R17: =IFERROR(Q17/C17,"") -> 0.11356378
A18: 全部门店总业绩 | C18: =SUM(数据源表A!F:F) -> 115631.46 | D18: =SUM(数据源表A!H:H) -> 80431.83 | E18: =SUM(数据源表A!I:I) -> 2575 | F18: =SUM(数据源表A!U:U) -> 55093.29 | G18: =SUM(数据源表A!AA:AA) -> 135.8 | H18: =SUM(数据源表A!AG:AG) -> 12966.29 | I18: =SUM(数据源表A!AM:AM) -> 10506.09 | J18: =SUM(数据源表A!AS:AS) -> 1730.36 | K18: =SUM(INDEX(数据源表A!$A:$CA,0,MATCH(K$5,数据源表A!$2:$2,0))) -> 776 | L18: =IFERROR(SUM(INDEX(数据源表A!$A:$CA,0,MATCH("美团/大众点评团购",数据源表A!$2:$2,0))),0)+IFERROR(SUM(INDEX(数据源表A!$A:$CA,0,MATCH("美团/大众点评支付",数据源表A!$2:$2,0))),0) -> 3049.08 | M18: =SUM(INDEX(数据源表A!$A:$CA,0,MATCH(M$5,数据源表A!$2:$2,0))) -> 4863.67 | N18: =SUM(INDEX(数据源表A!$A:$CA,0,MATCH(N$5,数据源表A!$2:$2,0))) -> 945.67 | O18: =IFERROR(SUM(INDEX(数据源表A!$A:$CA,0,MATCH(O$5,数据源表A!$2:$2,0))),0) -> 0 | P18: =F18+G18-L18-M18-K18-N18-O18 -> 45594.67 | Q18: =SUM(数据源表A!G:G) -> 35199.63 | R18: =IFERROR(Q18/C18,"") -> 0.30441222
A20: 门店名称 | B20: 营业额 | C20: 实收 | D20: 有效订单 | E20: 优惠金额 | F20: 优惠占比 | G20: 堂食收入 | H20: 堂食收入占比 | AE20: 折前单均 | AF20: 折后单均
A21: 鹅太公烧鹅（坂田店） | B21: =SUMIFS(数据源表A!F:F,数据源表A!B:B,$A$21,数据源表A!C:C,A3) -> 8178.26 | C21: =SUMIFS(数据源表A!H:H,数据源表A!B:B,$A$21,数据源表A!C:C,A3) -> 5133.67 | D21: =SUMIFS(数据源表A!I:I,数据源表A!B:B,$A$21,数据源表A!C:C,A3) -> 166 | E21: =SUMIFS(数据源表A!G:G,数据源表A!B:B,$A$21,数据源表A!C:C,A3) -> 3044.59 | F21: =IFERROR(E21/B21,0) -> 0.37227846 | G21: =C21-B23-E23-H23-B25-D25 -> 1713.2 | H21: =G21/C21 -> 0.33371837
B22: 美团外卖 | C22: 美团单量 | D22: 实收占比 | E22: 淘宝闪购 | F22: 淘宝闪购单量 | G22: 实收占比 | H22: 京东外卖 | I22: 京东单量 | J22: 实收占比
B23: =SUMIFS(数据源表A!AG:AG,数据源表A!B:B,$A$21,数据源表A!C:C,A3) -> 1633.27 | C23: =SUMIFS(数据源表A!AI:AI,数据源表A!B:B,$A$21,数据源表A!C:C,A3) -> 56 | D23: =IFERROR(B23/C21,0) -> 0.31814861 | E23: =SUMIFS(数据源表A!AM:AM,数据源表A!B:B,$A$21,数据源表A!C:C,A3) -> 951.08 | F23: =SUMIFS(数据源表A!AO:AO,数据源表A!B:B,$A$21,数据源表A!C:C,A3) -> 38 | G23: =IFERROR(E23/C21,0) -> 0.18526317 | H23: =SUMIFS(数据源表A!AS:AS,数据源表A!B:B,$A$21,数据源表A!C:C,A3) -> 104.2 | I23: =SUMIFS(数据源表A!AU:AU,数据源表A!B:B,$A$21,数据源表A!C:C,A3) -> 4 | J23: =IFERROR(H23/C21,0) -> 0.02029737
B24: 美团团购 | C24: 实收占比 | D24: 抖音团购 | E24: 实收占比 | F24: 美团一键买单 | G24: 实收占比 | H24: 储值消费 | I24: 实收占比 | J24: 优惠券 | K24: 实收占比
B25: =IFERROR(SUMIF(数据源表A!$B:$B,A21,INDEX(数据源表A!$A:$CA,0,MATCH("美团/大众点评团购",数据源表A!$2:$2,0))),0)+IFERROR(SUMIF(数据源表A!$B:$B,A21,INDEX(数据源表A!$A:$CA,0,MATCH("美团/大众点评支付",数据源表A!$2:$2,0))),0) -> 519.32 | C25: =IFERROR(B25/C21,0) -> 0.1011596 | D25: =SUMIF(数据源表A!$B:$B,A21,INDEX(数据源表A!$A:$CA,0,MATCH(D24,数据源表A!$2:$2,0))) -> 212.6 | E25: =IFERROR(D25/C21,0) -> 0.041412868 | F25: =SUMIF(数据源表A!$B:$B,A21,INDEX(数据源表A!$A:$CA,0,MATCH(K$5,数据源表A!$2:$2,0))) -> 0 | G25: =IFERROR(F25/C21,0) -> 0 | H25: =SUMIF(数据源表A!$B:$B,A21,INDEX(数据源表A!$A:$CA,0,MATCH(N$5,数据源表A!$2:$2,0))) -> 0 | I25: =IFERROR(H25/C21,0) -> 0 | J25: =IFERROR(SUMIF(数据源表A!$B:$B,A21,INDEX(数据源表A!$A:$CA,0,MATCH(O$5,数据源表A!$2:$2,0))),0) -> 0 | K25: =IFERROR(J25/E21,0) -> 0

Sheet 数据源表A
A1: 城市 | B1: 门店 | C1: 营业日 | D1: 门店创建时间 | E1: 营业天数 | F1: 营业额(元) | G1: 优惠金额(元) | H1: 营业收入(元) | I1: 订单量 | J1: 用餐人数 | K1: 消费桌数 | L1: 折前人均(元) | M1: 折后人均(元) | N1: 折前单均(元) | O1: 折后单均(元) | P1: 开台率 | Q1: 翻台率 | R1: 上座率 | S1: 平均用餐时长(分钟) | T1: 渠道营业构成 | AX1: 销售品项收入构成 | BF1: 营业收入构成 | BN1: 支付优惠构成 | CX1: 折扣优惠构成
T2: 店内销售 | Z2: 自提销售 | AF2: 美团外卖 | AL2: 淘宝闪购 | AR2: 京东秒送 | AX2: 菜品销售 | BB2: 外卖餐盒费 | BF2: 现金 | BG2: 扫码支付 | BH2: 会员卡 | BI2: 美团/大众点评团购 | BJ2: 抖音团购 | BK2: 一键买单（尾款） | BL2: 外卖 | BM2: 小计 | BN2: 会员卡 | BO2: 美团/大众点评团购 | CC2: 抖音团购 | CT2: 外卖 | CW2: 小计 | CX2: 手动折扣 | DD2: 店内促销 | DF2: 会员权益 | DH2: 优惠券 | DI2: 抹零 | DJ2: 小计
T3: 营业额(元) | U3: 营业收入(元) | V3: 优惠金额(元) | W3: 订单量 | X3: 折前单均(元) | Y3: 折后单均(元) | Z3: 营业额(元) | AA3: 营业收入(元) | AB3: 优惠金额(元) | AC3: 订单量 | AD3: 折前单均(元) | AE3: 折后单均(元) | AF3: 营业额(元) | AG3: 营业收入(元) | AH3: 优惠金额(元) | AI3: 订单量 | AJ3: 折前单均(元) | AK3: 折后单均(元) | AL3: 营业额(元) | AM3: 营业收入(元) | AN3: 优惠金额(元) | AO3: 订单量 | AP3: 折前单均(元) | AQ3: 折后单均(元) | AR3: 营业额(元) | AS3: 营业收入(元) | AT3: 优惠金额(元) | AU3: 订单量 | AV3: 折前单均(元) | AW3: 折后单均(元) | AX3: 营业额(元) | AY3: 营业收入(元) | AZ3: 优惠金额(元) | BA3: 菜品销量 | BB3: 营业额(元) | BC3: 营业收入(元) | BD3: 优惠金额(元) | BE3: 菜品销量 | BN3: 卡余额消费-赠送余额 | BO3: 【太公烧味】100元代金券 | BP3: 【招牌必点】太公烧鹅拼叉烧饭单人餐（含柠檬茶+靓汤） | BQ3: 【斩料节专享】金牌烧鸭饭+柠檬茶单人餐（含靓汤/小菜） | BR3: 【新品尝鲜】葱香叉烧滑蛋饭+上头柠檬茶（含靓汤） | BS3: 【新品尝鲜】葱香叉烧滑蛋饭（含柠檬茶+靓汤） | BT3: 【每日限量】战斧大鹅翅濑粉单人餐（现熬生地汤底） | BU3: 【超值】金牌烧鸭饭+柠檬茶（含靓汤/小菜） | BV3: 【超值优惠】50元代金券 | BW3: 太公招牌烧鹅三宝饭+柠檬茶 | BX3: 干饭双人餐-工作日特惠 | BY3: 暑期福利-招牌烧鹅（约100g） | BZ3: 美团团购 | CA3: 超值加料-金牌烧鸭100g | CB3: 鸡-鸭-鹅畅享四人餐 | CC3: 100元代金券太公烧味 | CD3: 50元代金券全场通用 | CE3: 【太公推荐】金牌烧鸭拼叉烧饭单人餐（含靓汤+柠檬茶） | CF3: 【太公爆品】金牌烧鸭饭+柠檬茶单人餐（含靓汤/小菜） | CG3: 【抖音】【太公推荐】金牌烧鸭拼叉烧饭单人餐（含靓汤+柠檬茶） | CH3: 【抖音】【斩料节专享】太公烧鹅拼叉烧饭单人餐（含靓汤+柠檬茶） | CI3: 【抖音】【每日限量】战斧大鹅翅烧鹅濑粉(现熬生地汤底) | CJ3: 【斩料节专享】太公烧鹅拼叉烧饭单人餐（含靓汤+柠檬茶） | CK3: 【斩料节专享】金牌烧鸭半只（砍料外带） | CL3: 【新品尝鲜】葱香叉烧滑蛋饭+柠檬茶单人餐（含靓汤/小菜） | CM3: 【暑价特惠】蜜汁叉烧饭单人餐（含例汤+柠檬茶） | CN3: 【每日限量】战斧大鹅翅烧鹅濑粉(现熬生地汤底) | CO3: 【点亮门店】上头柠檬茶一杯 | CP3: 【鲜烧鲜卖】金牌烧鸭+叉烧例牌双人餐（含时蔬/柠檬茶） | CQ3: 太公招牌烧鹅三宝饭+柠檬茶 | CR3: 干饭双人餐-工作日特惠 | CS3: （超值单品）金牌烧鸭100g | CT3: 美团外卖 | CU3: 淘宝闪购 | CV3: 京东秒送 | CX3: 手动赠菜 | CY3: 菜品手动8折 | CZ3: 菜品手动9折 | DA3: 订单手动8.8折 | DB3: 订单手动8折 | DC3: 订单手动减免 | DD3: 保利上城店开业活动 | DE3: 未来店7.13-7.16试营业8.8折 | DF3: 会员价 | DG3: 购招牌双拼饭换购柠檬茶-鹅太公 | DH3: 【金鹅卡】5元代金券 | DI3: 手动抹零
A4: 惠州市 | B4: 鹅太公烧鹅（上排店） | C4: 2026/07/15 | D4: 2025-09-24 15:34:42 | E4: 1 | F4: 3695.02 | G4: 1446.73 | H4: 2248.29 | I4: 93 | J4: 46 | K4: 8 | L4: 80.33 | M4: 48.88 | N4: 39.73 | O4: 24.18 | P4: 0.2667 | Q4: 0 | R4: 0.3833 | S4: 1 | T4: 1381.52 | U4: 1272.32 | V4: 109.2 | W4: 40 | X4: 34.54 | Y4: 31.81 | Z4: 0 | AA4: 0 | AB4: 0 | AC4: 0 | AD4: 0 | AE4: 0 | AF4: 985.2 | AG4: 427.09 | AH4: 558.11 | AI4: 19 | AJ4: 51.85 | AK4: 22.48 | AL4: 1044.9 | AM4: 432.07 | AN4: 612.83 | AO4: 26 | AP4: 40.19 | AQ4: 16.62 | AR4: 283.4 | AS4: 116.81 | AT4: 166.59 | AU4: 8 | AV4: 35.43 | AW4: 14.6 | AX4: 3626.22 | AY4: 2219.97 | AZ4: 1406.25 | BA4: 124.24 | BB4: 68.8 | BC4: 28.32 | BD4: 40.48 | BE4: 50 | BF4: 71 | BG4: 963.52 | BH4: 0 | BI4: 64.4 | BJ4: 173.4 | BK4: 0 | BL4: 975.97 | BM4: 2248.29 | BN4: 0 | BO4: 0 | BP4: 0 | BQ4: 52.8 | BR4: 0 | BS4: 0 | BT4: 4.2 | BU4: 0 | BV4: 0 | BW4: 0 | BX4: 0 | BY4: 0 | BZ4: 0 | CA4: 0 | CB4: 0 | CC4: 0 | CD4: 0 | CE4: 22 | CF4: 0 | CG4: 0 | CH4: 0 | CI4: 0 | CJ4: 0 | CK4: 22.4 | CL4: 0 | CM4: 0 | CN4: 5.2 | CO4: 1.2 | CP4: 0 | CQ4: 0 | CR4: 0 | CS4: 0 | CT4: 558.11 | CU4: 612.83 | CV4: 166.59 | CW4: 1445.33 | CX4: 0 | CY4: 0 | CZ4: 0 | DA4: 0 | DB4: 0 | DC4: 0 | DD4: 0 | DE4: 0 | DF4: 1.2 | DG4: 0 | DH4: 0 | DI4: 0.2 | DJ4: 1.4
A5: 惠州市 | B5: 鹅太公烧鹅（下埔店） | C5: 2026/07/15 | D5: 2025-09-20 15:53:45 | E5: 1 | F5: 5924.51 | G5: 1614.96 | H5: 4309.55 | I5: 140 | J5: 93 | K5: 24 | L5: 63.7 | M5: 46.34 | N5: 42.32 | O5: 30.78 | P5: 0.9231 | Q5: 0 | R5: 0.8942 | S5: 1 | T5: 3024.85 | U5: 2982.35 | V5: 42.5 | W5: 81 | X5: 37.34 | Y5: 36.82 | Z5: 0 | AA5: 0 | AB5: 0 | AC5: 0 | AD5: 0 | AE5: 0 | AF5: 1111.6 | AG5: 586.99 | AH5: 524.61 | AI5: 18 | AJ5: 61.76 | AK5: 32.61 | AL5: 1144.87 | AM5: 464.87 | AN5: 680 | AO5: 23 | AP5: 49.78 | AQ5: 20.21 | AR5: 643.19 | AS5: 275.34 | AT5: 367.85 | AU5: 18 | AV5: 35.73 | AW5: 15.3 | AX5: 5833.71 | AY5: 4268.68 | AZ5: 1565.03 | BA5: 285.756 | BB5: 90.8 | BC5: 40.87 | BD5: 49.93 | BE5: 55 | BF5: 184 | BG5: 2403.85 | BH5: 36.2 | BI5: 105.2 | BJ5: 253.1 | BK5: 0 | BL5: 1327.2 | BM5: 4309.55 | BN5: 1.8 | BO5: 0 | BP5: 6 | BQ5: 0 | BR5: 0 | BS5: 0 | BT5: 5.2 | BU5: 0 | BV5: 0 | BW5: 0 | BX5: 0 | BY5: 0 | BZ5: 0 | CA5: 0 | CB5: 0 | CC5: 0 | CD5: 0 | CE5: 17.5 | CF5: 0 | CG5: 0 | CH5: 0 | CI5: 0 | CJ5: 8 | CK5: 0 | CL5: 4 | CM5: 0 | CN5: 0 | CO5: 0 | CP5: 0 | CQ5: 0 | CR5: 0 | CS5: 0 | CT5: 524.61 | CU5: 680 | CV5: 367.85 | CW5: 1614.96 | CX5: 0 | CY5: 0 | CZ5: 0 | DA5: 0 | DB5: 0 | DC5: 0 | DD5: 0 | DE5: 0 | DF5: 0 | DG5: 0 | DH5: 0 | DI5: 0 | DJ5: 0
A6: 惠州市 | B6: 鹅太公烧鹅（东平三院店） | C6: 2026/07/15 | D6: 2026-04-29 11:14:45 | E6: 1 | F6: 3425.3 | G6: 388.99 | H6: 3036.31 | I6: 92 | J6: 108 | K6: 30 | L6: 31.72 | M6: 28.11 | N6: 37.23 | O6: 33 | P6: 2.3077 | Q6: 1.3077 | R6: 2.0769 | S6: 1 | T6: 2792.8 | U6: 2754.9 | V6: 37.9 | W6: 80 | X6: 34.91 | Y6: 34.44 | Z6: 0 | AA6: 0 | AB6: 0 | AC6: 0 | AD6: 0 | AE6: 0 | AF6: 632.5 | AG6: 281.41 | AH6: 351.09 | AI6: 12 | AJ6: 52.71 | AK6: 23.45 | AL6: 0 | AM6: 0 | AN6: 0 | AO6: 0 | AP6: 0 | AQ6: 0 | AR6: 0 | AS6: 0 | AT6: 0 | AU6: 0 | AV6: 0 | AW6: 0 | AX6: 3411.8 | AY6: 3030.31 | AZ6: 381.49 | BA6: 148.1 | BB6: 13.5 | BC6: 6 | BD6: 7.5 | BE6: 10 | BF6: 39 | BG6: 2551 | BH6: 0 | BI6: 61.6 | BJ6: 103.3 | BK6: 0 | BL6: 281.41 | BM6: 3036.31 | BN6: 0 | BO6: 0 | BP6: 0 | BQ6: 0 | BR6: 0 | BS6: 0 | BT6: 10.4 | BU6: 0 | BV6: 0 | BW6: 0 | BX6: 0 | BY6: 0 | BZ6: 0 | CA6: 0 | CB6: 0 | CC6: 0 | CD6: 0 | CE6: 24.5 | CF6: 0 | CG6: 0 | CH6: 0 | CI6: 0 | CJ6: 3 | CK6: 0 | CL6: 0 | CM6: 0 | CN6: 0 | CO6: 0 | CP6: 0 | CQ6: 0 | CR6: 0 | CS6: 0 | CT6: 351.09 | CU6: 0 | CV6: 0 | CW6: 388.99 | CX6: 0 | CY6: 0 | CZ6: 0 | DA6: 0 | DB6: 0 | DC6: 0 | DD6: 0 | DE6: 0 | DF6: 0 | DG6: 0 | DH6: 0 | DI6: 0 | DJ6: 0
A7: 惠州市 | B7: 鹅太公烧鹅（东平半岛店） | C7: 2026/07/15 | D7: 2026-03-28 15:48:48 | E7: 1 | F7: 5636.46 | G7: 2152.86 | H7: 3483.6 | I7: 130 | J7: 88 | K7: 29 | L7: 64.05 | M7: 39.59 | N7: 43.36 | O7: 26.8 | P7: 1.2083 | Q7: 0.2083 | R7: 0.9167 | S7: 1 | T7: 2883.27 | U7: 2356.48 | V7: 526.79 | W7: 78 | X7: 36.97 | Y7: 30.21 | Z7: 0 | AA7: 0 | AB7: 0 | AC7: 0 | AD7: 0 | AE7: 0 | AF7: 1271.6 | AG7: 531.69 | AH7: 739.91 | AI7: 22 | AJ7: 57.8 | AK7: 24.17 | AL7: 1377.19 | AM7: 536.03 | AN7: 841.16 | AO7: 27 | AP7: 51.01 | AQ7: 19.85 | AR7: 104.4 | AS7: 59.4 | AT7: 45 | AU7: 3 | AV7: 34.8 | AW7: 19.8 | AX7: 5575.86 | AY7: 3455.84 | AZ7: 2120.02 | BA7: 188.365 | BB7: 60.6 | BC7: 27.76 | BD7: 32.84 | BE7: 46 | BF7: 54 | BG7: 1387.17 | BH7: 68.58 | BI7: 236.3 | BJ7: 608.43 | BK7: 2 | BL7: 1127.12 | BM7: 3483.6 | BN7: 3.42 | BO7: 0 | BP7: 45.6 | BQ7: 0 | BR7: 0 | BS7: 15.2 | BT7: 0 | BU7: 0 | BV7: 15 | BW7: 0 | BX7: 0 | BY7: 0 | BZ7: 0 | CA7: 0 | CB7: 0 | CC7: 0 | CD7: 13.1 | CE7: 352.3 | CF7: 0 | CG7: 0 | CH7: 0 | CI7: 0 | CJ7: 45.6 | CK7: 0 | CL7: 0 | CM7: 7.2 | CN7: 11.4 | CO7: 17.97 | CP7: 0 | CQ7: 0 | CR7: 0 | CS7: 0 | CT7: 739.91 | CU7: 841.16 | CV7: 45 | CW7: 2152.86 | CX7: 0 | CY7: 0 | CZ7: 0 | DA7: 0 | DB7: 0 | DC7: 0 | DD7: 0 | DE7: 0 | DF7: 0 | DG7: 0 | DH7: 0 | DI7: 0 | DJ7: 0
A8: 深圳市 | B8: 鹅太公烧鹅（保利上城店） | C8: 2026/07/15 | D8: 2026-07-07 11:42:16 | E8: 1 | F8: 5174.4 | G8: 633.94 | H8: 4540.46 | I8: 100 | J8: 116 | K8: 35 | L8: 44.61 | M8: 39.14 | N8: 51.74 | O8: 45.4 | P8: 1.6667 | Q8: 0.6667 | R8: 2.0714 | S8: 1 | T8: 5174.4 | U8: 4540.46 | V8: 633.94 | W8: 100 | X8: 51.74 | Y8: 45.4 | Z8: 0 | AA8: 0 | AB8: 0 | AC8: 0 | AD8: 0 | AE8: 0 | AF8: 0 | AG8: 0 | AH8: 0 | AI8: 0 | AJ8: 0 | AK8: 0 | AL8: 0 | AM8: 0 | AN8: 0 | AO8: 0 | AP8: 0 | AQ8: 0 | AR8: 0 | AS8: 0 | AT8: 0 | AU8: 0 | AV8: 0 | AW8: 0 | AX8: 5174.4 | AY8: 4540.46 | AZ8: 633.94 | BA8: 147.46 | BB8: 0 | BC8: 0 | BD8: 0 | BE8: 0 | BF8: 98 | BG8: 4262.51 | BH8: 179.95 | BI8: 0 | BJ8: 0 | BK8: 0 | BL8: 0 | BM8: 4540.46 | BN8: 10.13 | BO8: 0 | BP8: 0 | BQ8: 0 | BR8: 0 | BS8: 0 | BT8: 0 | BU8: 0 | BV8: 0 | BW8: 0 | BX8: 0 | BY8: 0 | BZ8: 0 | CA8: 0 | CB8: 0 | CC8: 0 | CD8: 0 | CE8: 0 | CF8: 0 | CG8: 0 | CH8: 0 | CI8: 0 | CJ8: 0 | CK8: 0 | CL8: 0 | CM8: 0 | CN8: 0 | CO8: 0 | CP8: 0 | CQ8: 0 | CR8: 0 | CS8: 0 | CT8: 0 | CU8: 0 | CV8: 0 | CW8: 10.13 | CX8: 0 | CY8: 0 | CZ8: 0 | DA8: 0 | DB8: 0 | DC8: 0 | DD8: 584.57 | DE8: 0 | DF8: 28.8 | DG8: 9 | DH8: 0 | DI8: 1.44 | DJ8: 623.81
A9: 惠州市 | B9: 鹅太公烧鹅（华侨城店） | C9: 2026/07/15 | D9: 2025-11-06 12:57:48 | E9: 1 | F9: 5649.76 | G9: 1572.41 | H9: 4077.35 | I9: 112 | J9: 79 | K9: 18 | L9: 71.52 | M9: 51.61 | N9: 50.44 | O9: 36.4 | P9: 0.6 | Q9: 0 | R9: 0.6583 | S9: 1 | T9: 3056.81 | U9: 2958.72 | V9: 98.09 | W9: 67 | X9: 45.62 | Y9: 44.16 | Z9: 0 | AA9: 0 | AB9: 0 | AC9: 0 | AD9: 0 | AE9: 0 | AF9: 1168.47 | AG9: 485.15 | AH9: 683.32 | AI9: 24 | AJ9: 48.69 | AK9: 20.21 | AL9: 1424.48 | AM9: 633.48 | AN9: 791 | AO9: 21 | AP9: 67.83 | AQ9: 30.17 | AR9: 0 | AS9: 0 | AT9: 0 | AU9: 0 | AV9: 0 | AW9: 0 | AX9: 5591.66 | AY9: 4052.82 | AZ9: 1538.84 | BA9: 174.176 | BB9: 58.1 | BC9: 24.53 | BD9: 33.57 | BE9: 42 | BF9: 0 | BG9: 2574 | BH9: 0 | BI9: 92.6 | BJ9: 291.12 | BK9: 1 | BL9: 1118.63 | BM9: 4077.35 | BN9: 0 | BO9: 0 | BP9: 3 | BQ9: 0 | BR9: 0 | BS9: 0 | BT9: 0 | BU9: 0 | BV9: 5 | BW9: 0 | BX9: 0 | BY9: 0 | BZ9: 0 | CA9: 0 | CB9: 0 | CC9: 0 | CD9: 0 | CE9: 27.5 | CF9: 0 | CG9: 0 | CH9: 0 | CI9: 0 | CJ9: 4 | CK9: 0 | CL9: 0 | CM9: 2 | CN9: 10.4 | CO9: 15.98 | CP9: 14 | CQ9: 0 | CR9: 0 | CS9: 0 | CT9: 683.32 | CU9: 791 | CV9: 0 | CW9: 1556.2 | CX9: 12 | CY9: 0 | CZ9: 0 | DA9: 1.92 | DB9: 0 | DC9: 2 | DD9: 0 | DE9: 0 | DF9: 0 | DG9: 0 | DH9: 0 | DI9: 0.29 | DJ9: 16.21
A10: 惠州市 | B10: 鹅太公烧鹅（博罗店） | C10: 2026/07/15 | D10: 2025-12-01 13:02:59 | E10: 1 | F10: 9381.7 | G10: 3255.19 | H10: 6126.51 | I10: 219 | J10: 128 | K10: 26 | L10: 73.29 | M10: 47.86 | N10: 42.84 | O10: 27.97 | P10: 0.8667 | Q10: 0 | R10: 1.0667 | S10: 1 | T10: 4437.6 | U10: 4296.12 | V10: 141.48 | W10: 119 | X10: 37.29 | Y10: 36.1 | Z10: 0 | AA10: 0 | AB10: 0 | AC10: 0 | AD10: 0 | AE10: 0 | AF10: 1871.7 | AG10: 874.4 | AH10: 997.3 | AI10: 33 | AJ10: 56.72 | AK10: 26.5 | AL10: 3072.4 | AM10: 955.99 | AN10: 2116.41 | AO10: 67 | AP10: 45.86 | AQ10: 14.27 | AR10: 0 | AS10: 0 | AT10: 0 | AU10: 0 | AV10: 0 | AW10: 0 | AX10: 9326.7 | AY10: 6104.06 | AZ10: 3222.64 | BA10: 442 | BB10: 55 | BC10: 22.45 | BD10: 32.55 | BE10: 39 | BF10: 256 | BG10: 3543.2 | BH10: 35.62 | BI10: 141.2 | BJ10: 320.1 | BK10: 0 | BL10: 1830.39 | BM10: 6126.51 | BN10: 2.38 | BO10: 0 | BP10: 67.2 | BQ10: 0 | BR10: 0 | BS10: 0 | BT10: 0 | BU10: 0 | BV10: 0 | BW10: 0 | BX10: 0 | BY10: 0 | BZ10: 0 | CA10: 0 | CB10: 0 | CC10: 0 | CD10: 6.1 | CE10: 36 | CF10: 0 | CG10: 0 | CH10: 0 | CI10: 0 | CJ10: 5 | CK10: 0 | CL10: 4 | CM10: 0 | CN10: 6.2 | CO10: 0 | CP10: 0 | CQ10: 0 | CR10: 0 | CS10: 0 | CT10: 997.3 | CU10: 2116.41 | CV10: 0 | CW10: 3240.59 | CX10: 0 | CY10: 0 | CZ10: 14.6 | DA10: 0 | DB10: 0 | DC10: 0 | DD10: 0 | DE10: 0 | DF10: 0 | DG10: 0 | DH10: 0 | DI10: 0 | DJ10: 14.6
A11: 深圳市 | B11: 鹅太公烧鹅（坂田店） | C11: 2026/07/15 | D11: 2026-03-20 20:18:08 | E11: 1 | F11: 8178.26 | G11: 3044.59 | H11: 5133.67 | I11: 166 | J11: 72 | K11: 32 | L11: 113.59 | M11: 71.3 | N11: 49.27 | O11: 30.93 | P11: 2.2857 | Q11: 1.2857 | R11: 1.2857 | S11: 2 | T11: 2795.68 | U11: 2398.12 | V11: 397.56 | W11: 66 | X11: 42.36 | Y11: 36.34 | Z11: 47 | AA11: 47 | AB11: 0 | AC11: 2 | AD11: 23.5 | AE11: 23.5 | AF11: 3110.58 | AG11: 1633.27 | AH11: 1477.31 | AI11: 56 | AJ11: 55.55 | AK11: 29.17 | AL11: 2058.8 | AM11: 951.08 | AN11: 1107.72 | AO11: 38 | AP11: 54.18 | AQ11: 25.03 | AR11: 166.2 | AS11: 104.2 | AT11: 62 | AU11: 4 | AV11: 41.55 | AW11: 26.05 | AX11: 8085.66 | AY11: 5081.33 | AZ11: 3004.33 | BA11: 206.664 | BB11: 92.6 | BC11: 52.34 | BD11: 40.26 | BE11: 78 | BF11: 54 | BG11: 1659.2 | BH11: 0 | BI11: 519.32 | BJ11: 212.6 | BK11: 0 | BL11: 2688.55 | BM11: 5133.67 | BN11: 0 | BO11: 7 | BP11: 0 | BQ11: 0 | BR11: 15.2 | BS11: 0 | BT11: 0 | BU11: 88.2 | BV11: 0 | BW11: 6 | BX11: 0 | BY11: 16.68 | BZ11: 0 | CA11: 0 | CB11: 48 | CC11: 0 | CD11: 0 | CE11: 0 | CF11: 55.8 | CG11: 0 | CH11: 0 | CI11: 0 | CJ11: 0 | CK11: 0 | CL11: 16.2 | CM11: 0 | CN11: 0 | CO11: 0 | CP11: 0 | CQ11: 47.4 | CR11: 45 | CS11: 0 | CT11: 1477.31 | CU11: 1107.72 | CV11: 62 | CW11: 2992.51 | CX11: 0 | CY11: 0 | CZ11: 0 | DA11: 0 | DB11: 24.2 | DC11: 0 | DD11: 0 | DE11: 0 | DF11: 21.6 | DG11: 0 | DH11: 5 | DI11: 1.28 | DJ11: 52.08
A12: 深圳市 | B12: 鹅太公烧鹅（方洲店） | C12: 2026/07/15 | D12: 2026-06-09 09:38:17 | E12: 1 | F12: 3972 | G12: 409.57 | H12: 3562.43 | I12: 76 | J12: 94 | K12: 30 | L12: 42.26 | M12: 37.9 | N12: 52.26 | O12: 46.87 | P12: 1.3636 | Q12: 0.3636 | R12: 1.0682 | S12: 1 | T12: 3972 | U12: 3562.43 | V12: 409.57 | W12: 76 | X12: 52.26 | Y12: 46.87 | Z12: 0 | AA12: 0 | AB12: 0 | AC12: 0 | AD12: 0 | AE12: 0 | AF12: 0 | AG12: 0 | AH12: 0 | AI12: 0 | AJ12: 0 | AK12: 0 | AL12: 0 | AM12: 0 | AN12: 0 | AO12: 0 | AP12: 0 | AQ12: 0 | AR12: 0 | AS12: 0 | AT12: 0 | AU12: 0 | AV12: 0 | AW12: 0 | AX12: 3972 | AY12: 3562.43 | AZ12: 409.57 | BA12: 144 | BB12: 0 | BC12: 0 | BD12: 0 | BE12: 0 | BF12: 45 | BG12: 2990.28 | BH12: 147.77 | BI12: 254.58 | BJ12: 124.8 | BK12: 0 | BL12: 0 | BM12: 3562.43 | BN12: 8.63 | BO12: 0 | BP12: 0 | BQ12: 0 | BR12: 0 | BS12: 0 | BT12: 0 | BU12: 125.4 | BV12: 0 | BW12: 75.6 | BX12: 0 | BY12: 25.02 | BZ12: 0 | CA12: 6.4 | CB12: 0 | CC12: 0 | CD12: 0 | CE12: 0 | CF12: 0 | CG12: 0 | CH12: 0 | CI12: 0 | CJ12: 0 | CK12: 0 | CL12: 0 | CM12: 0 | CN12: 0 | CO12: 0 | CP12: 0 | CQ12: 25.2 | CR12: 90 | CS12: 0 | CT12: 0 | CU12: 0 | CV12: 0 | CW12: 356.25 | CX12: 0 | CY12: 0 | CZ12: 0 | DA12: 15.72 | DB12: 0 | DC12: 0 | DD12: 0 | DE12: 0 | DF12: 37.6 | DG12: 0 | DH12: 0 | DI12: 0 | DJ12: 53.32
A13: 揭阳市 | B13: 鹅太公烧鹅（普宁店） | C13: 2026/07/15 | D13: 2025-08-14 21:26:09 | E13: 1 | F13: 6075.55 | G13: 2117.79 | H13: 3957.76 | I13: 164 | J13: 85 | K13: 40 | L13: 71.48 | M13: 46.56 | N13: 37.05 | O13: 24.13 | P13: 2.2222 | Q13: 1.2222 | R13: 0.5903 | S13: 1 | T13: 2313.2 | U13: 2236.42 | V13: 76.78 | W13: 69 | X13: 33.52 | Y13: 32.41 | Z13: 0 | AA13: 0 | AB13: 0 | AC13: 0 | AD13: 0 | AE13: 0 | AF13: 993.5 | AG13: 412.86 | AH13: 580.64 | AI13: 25 | AJ13: 39.74 | AK13: 16.51 | AL13: 1412.36 | AM13: 718.17 | AN13: 694.19 | AO13: 32 | AP13: 44.14 | AQ13: 22.44 | AR13: 1356.49 | AS13: 590.31 | AT13: 766.18 | AU13: 38 | AV13: 35.7 | AW13: 15.53 | AX13: 5919.05 | AY13: 3887.99 | AZ13: 2031.06 | BA13: 217 | BB13: 156.5 | BC13: 69.77 | BD13: 86.73 | BE13: 88 | BF13: 0 | BG13: 1809 | BH13: 21.91 | BI13: 23.8 | BJ13: 381.71 | BK13: 0 | BL13: 1721.34 | BM13: 3957.76 | BN13: 1.09 | BO13: 0 | BP13: 3 | BQ13: 0 | BR13: 0 | BS13: 0 | BT13: 0 | BU13: 0 | BV13: 0 | BW13: 0 | BX13: 0 | BY13: 0 | BZ13: 0 | CA13: 0 | CB13: 0 | CC13: 0 | CD13: 0 | CE13: 8.5 | CF13: 0 | CG13: 0 | CH13: 1 | CI13: 2.2 | CJ13: 24 | CK13: 0 | CL13: 3 | CM13: 0 | CN13: 0 | CO13: 5.99 | CP13: 28 | CQ13: 0 | CR13: 0 | CS13: 0 | CT13: 580.64 | CU13: 694.19 | CV13: 766.18 | CW13: 2117.79 | CX13: 0 | CY13: 0 | CZ13: 0 | DA13: 0 | DB13: 0 | DC13: 0 | DD13: 0 | DE13: 0 | DF13: 0 | DG13: 0 | DH13: 0 | DI13: 0 | DJ13: 0
A14: 揭阳市 | B14: 鹅太公烧鹅（普宁溪尾店） | C14: 2026/07/15 | D14: 2026-01-21 11:36:33 | E14: 1 | F14: 7770.7 | G14: 2177.55 | H14: 5593.15 | I14: 189 | J14: 92 | K14: 19 | L14: 84.46 | M14: 60.8 | N14: 41.11 | O14: 29.59 | P14: 1.1875 | Q14: 0.1875 | R14: 1.4375 | S14: 1 | T14: 3718.5 | U14: 3609.9 | V14: 108.6 | W14: 87 | X14: 42.74 | Y14: 41.49 | Z14: 0 | AA14: 0 | AB14: 0 | AC14: 0 | AD14: 0 | AE14: 0 | AF14: 2315.6 | AG14: 1119.58 | AH14: 1196.02 | AI14: 57 | AJ14: 40.62 | AK14: 19.64 | AL14: 1675.6 | AM14: 820.67 | AN14: 854.93 | AO14: 44 | AP14: 38.08 | AQ14: 18.65 | AR14: 61 | AS14: 43 | AT14: 18 | AU14: 1 | AV14: 61 | AW14: 43 | AX14: 7682.4 | AY14: 5548.82 | AZ14: 2133.58 | BA14: 294 | BB14: 88.3 | BC14: 44.33 | BD14: 43.97 | BE14: 57 | BF14: 198 | BG14: 2644.5 | BH14: 0 | BI14: 168.8 | BJ14: 598.6 | BK14: 0 | BL14: 1983.25 | BM14: 5593.15 | BN14: 0 | BO14: 0 | BP14: 3 | BQ14: 0 | BR14: 0 | BS14: 0 | BT14: 0 | BU14: 0 | BV14: 0 | BW14: 0 | BX14: 0 | BY14: 0 | BZ14: 0 | CA14: 0 | CB14: 0 | CC14: 0 | CD14: 0 | CE14: 49 | CF14: 0 | CG14: 11 | CH14: 0 | CI14: 0 | CJ14: 22 | CK14: 0 | CL14: 16 | CM14: 0 | CN14: 5.2 | CO14: 2.4 | CP14: 0 | CQ14: 0 | CR14: 0 | CS14: 0 | CT14: 1196.02 | CU14: 854.93 | CV14: 18 | CW14: 2177.55 | CX14: 0 | CY14: 0 | CZ14: 0 | DA14: 0 | DB14: 0 | DC14: 0 | DD14: 0 | DE14: 0 | DF14: 0 | DG14: 0 | DH14: 0 | DI14: 0 | DJ14: 0
A15: 深圳市 | B15: 鹅太公烧鹅（未来花园店） | C15: 2026/07/15 | D15: 2026-07-07 11:40:46 | E15: 1 | F15: 9258.4 | G15: 1160.08 | H15: 8098.32 | I15: 176 | J15: 228 | K15: 90 | L15: 40.61 | M15: 35.52 | N15: 52.6 | O15: 46.01 | P15: 5 | Q15: 4 | R15: 4.0714 | S15: 1 | T15: 9258.4 | U15: 8098.32 | V15: 1160.08 | W15: 176 | X15: 52.6 | Y15: 46.01 | Z15: 0 | AA15: 0 | AB15: 0 | AC15: 0 | AD15: 0 | AE15: 0 | AF15: 0 | AG15: 0 | AH15: 0 | AI15: 0 | AJ15: 0 | AK15: 0 | AL15: 0 | AM15: 0 | AN15: 0 | AO15: 0 | AP15: 0 | AQ15: 0 | AR15: 0 | AS15: 0 | AT15: 0 | AU15: 0 | AV15: 0 | AW15: 0 | AX15: 9258.4 | AY15: 8098.32 | AZ15: 1160.08 | BA15: 294 | BB15: 0 | BC15: 0 | BD15: 0 | BE15: 0 | BF15: 130.24 | BG15: 7638.34 | BH15: 329.74 | BI15: 0 | BJ15: 0 | BK15: 0 | BL15: 0 | BM15: 8098.32 | BN15: 16.9 | BO15: 0 | BP15: 0 | BQ15: 0 | BR15: 0 | BS15: 0 | BT15: 0 | BU15: 0 | BV15: 0 | BW15: 0 | BX15: 0 | BY15: 0 | BZ15: 0 | CA15: 0 | CB15: 0 | CC15: 0 | CD15: 0 | CE15: 0 | CF15: 0 | CG15: 0 | CH15: 0 | CI15: 0 | CJ15: 0 | CK15: 0 | CL15: 0 | CM15: 0 | CN15: 0 | CO15: 0 | CP15: 0 | CQ15: 0 | CR15: 0 | CS15: 0 | CT15: 0 | CU15: 0 | CV15: 0 | CW15: 16.9 | CX15: 0 | CY15: 0 | CZ15: 0 | DA15: 0 | DB15: 0 | DC15: 0 | DD15: 0 | DE15: 1049.58 | DF15: 93.6 | DG15: 0 | DH15: 0 | DI15: 0 | DJ15: 1143.18
... A21: 深圳市 | B21: 鹅太公烧鹅（龙岗万科店） | C21: 2026/07/15 | D21: 2026-03-20 20:17:08 | E21: 1 | F21: 9979.48 | G21: 4103.78 | H21: 5875.7 | I21: 179 | J21: 70 | K21: 17 | L21: 142.56 | M21: 83.94 | N21: 55.75 | O21: 32.83 | P21: 0.8947 | Q21: 0 | R21: 0.9211 | S21: 1 | T21: 3282.2 | U21: 2736.87 | V21: 545.33 | W21: 65 | X21: 50.5 | Y21: 42.11 | Z21: 0 | AA21: 0 | AB21: 0 | AC21: 0 | AD21: 0 | AE21: 0 | AF21: 4080.19 | AG21: 1980.31 | AH21: 2099.88 | AI21: 64 | AJ21: 63.75 | AK21: 30.94 | AL21: 2617.09 | AM21: 1158.52 | AN21: 1458.57 | AO21: 50 | AP21: 52.34 | AQ21: 23.17 | AR21: 0 | AS21: 0 | AT21: 0 | AU21: 0 | AV21: 0 | AW21: 0 | AX21: 9887.78 | AY21: 5826.8 | AZ21: 4060.98 | BA21: 258.1 | BB21: 91.7 | BC21: 48.9 | BD21: 42.8 | BE21: 72 | BF21: 40 | BG21: 1844 | BH21: 2.09 | BI21: 503.38 | BJ21: 339.4 | BK21: 8 | BL21: 3138.83 | BM21: 5875.7 | BN21: 0.11 | BO21: 8 | BP21: 0 | BQ21: 0 | BR21: 15.2 | BS21: 0 | BT21: 0 | BU21: 120.6 | BV21: 0 | BW21: 97.8 | BX21: 90 | BY21: 25.02 | BZ21: 0 | CA21: 0 | CB21: 0 | CC21: 15 | CD21: 0 | CE21: 0 | CF21: 81 | CG21: 0 | CH21: 0 | CI21: 0 | CJ21: 0 | CK21: 0 | CL21: 0 | CM21: 0 | CN21: 0 | CO21: 0 | CP21: 0 | CQ21: 50.4 | CR21: 0 | CS21: 3.2 | CT21: 2099.88 | CU21: 1458.57 | CV21: 0 | CW21: 4064.78 | CX21: 0 | CY21: 12.8 | CZ21: 0 | DA21: 0 | DB21: 0 | DC21: 0 | DD21: 0 | DE21: 0 | DF21: 23.2 | DG21: 3 | DH21: 0 | DI21: 0 | DJ21: 39
